app.py
doc.py
dAngr/run.py
dAngr/angr_ext/connection.py
dAngr/angr_ext/debugger.py
dAngr/angr_ext/models.py
dAngr/angr_ext/std_tracker.py
dAngr/angr_ext/step_handler.py
dAngr/angr_ext/utils.py
dAngr/cli/__init__.py
dAngr/cli/cli_connection.py
dAngr/cli/command_line_debugger.py
dAngr/cli/filters.py
dAngr/cli/less_view.py
dAngr/cli/models.py
dAngr/cli/pretty_print.py
dAngr/cli/script_processor.py
dAngr/cli/server.py
dAngr/cli/state_visualizer.py
dAngr/cli/debugger_commands/__init__.py
dAngr/cli/debugger_commands/base.py
dAngr/cli/debugger_commands/breakpoints.py
dAngr/cli/debugger_commands/exclusions.py
dAngr/cli/debugger_commands/execution.py
dAngr/cli/debugger_commands/files.py
dAngr/cli/debugger_commands/filters.py
dAngr/cli/debugger_commands/functions.py
dAngr/cli/debugger_commands/general.py
dAngr/cli/debugger_commands/info.py
dAngr/cli/debugger_commands/memory.py
dAngr/cli/debugger_commands/symbols.py
dAngr/cli/debugger_commands/tools.py
dAngr/cli/debugger_commands/viewer.py
dAngr/cli/grammar/control_flow.py
dAngr/cli/grammar/definitions.py
dAngr/cli/grammar/error_listener.py
dAngr/cli/grammar/execution_context.py
dAngr/cli/grammar/expressions.py
dAngr/cli/grammar/parser.py
dAngr/cli/grammar/script.py
dAngr/cli/grammar/statements.py
dAngr/cli/grammar/visitor.py
dAngr/cli/grammar/antlr/dAngrLexer.py
dAngr/cli/grammar/antlr/dAngrListener.py
dAngr/cli/grammar/antlr/dAngrParser.py
dAngr/cli/grammar/antlr/dAngrVisitor.py
dAngr/cli/grammar/antlr/lex.py
dAngr/cli/grammar/antlr/rangesLexer.py
dAngr/cli/grammar/antlr/rangesListener.py
dAngr/cli/grammar/antlr/rangesParser.py
dAngr/cli/grammar/antlr/rangesVisitor.py
dAngr/exceptions/CommandError.py
dAngr/exceptions/DebuggerCommandError.py
dAngr/exceptions/ExecutionError.py
dAngr/exceptions/FileNotFoundError.py
dAngr/exceptions/InvalidArgumentError.py
dAngr/exceptions/KeyError.py
dAngr/exceptions/ParseError.py
dAngr/exceptions/ValueError.py
dAngr/exceptions/__init__.py
dAngr/tools/document_gen.py
dAngr/utils/__init__.py
dAngr-0.0.13.dist-info/METADATA
dAngr-0.0.13.dist-info/WHEEL
dAngr-0.0.13.dist-info/entry_points.txt
dAngr-0.0.13.dist-info/top_level.txt
dAngr-0.0.13.dist-info/RECORD
