Metadata-Version: 2.2
Name: dAngr
Version: 0.0.13
Summary: Debugging with Angr package
Author-email: Jorn Lapon <jorn.lapon@kuleuven.be>, Dairo de Ruck <dairo.deruck@kuleuven.be>, Jef Jacobs <jef.jacobs@kuleuven.be>
Project-URL: Homepage, https://github.com/angr-debugging/dAngr
Project-URL: Issues, https://github.com/angr-debugging/dAngr/issues
Classifier: Programming Language :: Python :: 3
Classifier: Operating System :: OS Independent
Requires-Python: >=3.10
Requires-Dist: angr==9.2.94
Requires-Dist: pytest==8.1.1
Requires-Dist: prompt_toolkit==3.0.43
Requires-Dist: pytest-asyncio==0.23.6
Requires-Dist: asynctest==0.13.0
Requires-Dist: angr-utils==0.5.0
Requires-Dist: nest_asyncio==1.6.0
Requires-Dist: setuptools==72.1.0
Requires-Dist: multimethod==1.12
Requires-Dist: antlr4-python3-runtime==4.13.2
Requires-Dist: antlr4-tools==0.2.1
Requires-Dist: antlr-denter==1.3.1
